colors1/__init__.py
colors1/colors.py
colors1-0.0.2.dist-info/LICENSE
colors1-0.0.2.dist-info/METADATA
colors1-0.0.2.dist-info/WHEEL
colors1-0.0.2.dist-info/top_level.txt
colors1-0.0.2.dist-info/RECORD
