Metadata-Version: 2.1
Name: colors1
Version: 0.0.2
Summary: A package where some colors are defined. Very simple, but very useful.
Author-email: GameGuyOnYT <efeoyun@tahca.com>
Project-URL: Homepage, https://github.com/GameGuyOnYT/colors1-library
Project-URL: Bug Tracker, https://github.com/GameGuyOnYT/colors1-library/issues
Classifier: Programming Language :: Python :: 3
Classifier: License :: OSI Approved :: MIT License
Classifier: Operating System :: OS Independent
Requires-Python: >=3.7
License-File: LICENSE
